functions_by_xujajon89/README.md
functions_by_xujajon89/math_functions.py
functions_by_xujajon89-0.3.0.dist-info/WHEEL
functions_by_xujajon89-0.3.0.dist-info/METADATA
functions_by_xujajon89-0.3.0.dist-info/RECORD
